[
  {"id":1,"nombre":"Hotel Centro CDMX","imagen":"NA","calificacion":5,"precio":"$$$","estado":"Abierto","descripcion":"Hotel de lujo en el centro histórico.","horarios":"24h","telefono":"55 1234 5678","direccion":"Av. Reforma 100, CDMX","web":"NA","menu":"NA","servicio":"Hotel, WiFi, Desayuno"},
  {"id":2,"nombre":"Hostal Zócalo","imagen":"NA","calificacion":4,"precio":"$","estado":"Abierto","descripcion":"Hostal económico cerca del Zócalo.","horarios":"24h","telefono":"55 2345 6789","direccion":"Calle Madero 200, CDMX","web":"NA","menu":"NA","servicio":"Hostal, WiFi"},
  {"id":3,"nombre":"Suites Reforma","imagen":"NA","calificacion":5,"precio":"$$$","estado":"Abierto","descripcion":"Suites ejecutivas con alberca.","horarios":"24h","telefono":"55 3456 7890","direccion":"Av. Insurgentes 300, CDMX","web":"NA","menu":"NA","servicio":"Suites, Piscina"},
  {"id":4,"nombre":"Hotel Alameda","imagen":"NA","calificacion":4,"precio":"$$","estado":"Abierto","descripcion":"Hotel familiar frente a la Alameda.","horarios":"24h","telefono":"55 4567 8901","direccion":"Blvd. Aeropuerto 400, CDMX","web":"NA","menu":"NA","servicio":"Hotel, Restaurante"},
  {"id":5,"nombre":"Posada Juárez","imagen":"NA","calificacion":5,"precio":"$$","estado":"Abierto","descripcion":"Posada tradicional en el centro.","horarios":"24h","telefono":"55 5678 9012","direccion":"Av. Juárez 500, CDMX","web":"NA","menu":"NA","servicio":"Posada, WiFi"},
  {"id":6,"nombre":"Hotel Ejecutivo CDMX","imagen":"NA","calificacion":4,"precio":"$$$","estado":"Abierto","descripcion":"Hotel ejecutivo con centro de negocios.","horarios":"24h","telefono":"55 6789 0123","direccion":"Calle Hidalgo 600, CDMX","web":"NA","menu":"NA","servicio":"Hotel, Centro de Negocios"},
  {"id":7,"nombre":"Hostal Universitario CDMX","imagen":"NA","calificacion":3,"precio":"$","estado":"Abierto","descripcion":"Hostal para estudiantes y viajeros.","horarios":"24h","telefono":"55 7890 1234","direccion":"Av. Universidad 700, CDMX","web":"NA","menu":"NA","servicio":"Hostal, WiFi"},
  {"id":8,"nombre":"Hotel Boutique Centro","imagen":"NA","calificacion":5,"precio":"$$$","estado":"Abierto","descripcion":"Hotel boutique en el centro histórico.","horarios":"24h","telefono":"55 8901 2345","direccion":"Av. Madero 800, CDMX","web":"NA","menu":"NA","servicio":"Hotel Boutique"},
  {"id":9,"nombre":"Motel Express CDMX","imagen":"NA","calificacion":3,"precio":"$","estado":"Abierto","descripcion":"Motel económico y seguro.","horarios":"24h","telefono":"55 9012 3456","direccion":"Calle 16 de Septiembre 900, CDMX","web":"NA","menu":"NA","servicio":"Motel, Estacionamiento"},
  {"id":10,"nombre":"Hotel Tradición CDMX","imagen":"NA","calificacion":4,"precio":"$$","estado":"Abierto","descripcion":"Hotel tradicional con desayuno incluido.","horarios":"24h","telefono":"55 1234 5670","direccion":"Av. Reforma 1100, CDMX","web":"NA","menu":"NA","servicio":"Hotel, Desayuno"},
  {"id":11,"nombre":"Hotel Ejecutivo Reforma","imagen":"NA","calificacion":4,"precio":"$$$","estado":"Abierto","descripcion":"Hotel ejecutivo en Reforma.","horarios":"24h","telefono":"55 2345 6781","direccion":"Av. Insurgentes 1200, CDMX","web":"NA","menu":"NA","servicio":"Hotel, WiFi"},
  {"id":12,"nombre":"Hostal Centro CDMX","imagen":"NA","calificacion":3,"precio":"$","estado":"Abierto","descripcion":"Hostal céntrico y económico.","horarios":"24h","telefono":"55 3456 7892","direccion":"Av. Juárez 1300, CDMX","web":"NA","menu":"NA","servicio":"Hostal, WiFi"},
  {"id":13,"nombre":"Hotel Familiar CDMX","imagen":"NA","calificacion":4,"precio":"$$","estado":"Abierto","descripcion":"Hotel para familias y grupos.","horarios":"24h","telefono":"55 4567 8903","direccion":"Blvd. Aeropuerto 1400, CDMX","web":"NA","menu":"NA","servicio":"Hotel, Familiar"},
  {"id":14,"nombre":"Hotel Boutique Reforma","imagen":"NA","calificacion":5,"precio":"$$$","estado":"Abierto","descripcion":"Hotel boutique cerca de Reforma.","horarios":"24h","telefono":"55 5678 9014","direccion":"Av. Universidad 1700, CDMX","web":"NA","menu":"NA","servicio":"Hotel Boutique"},
  {"id":15,"nombre":"Motel Alameda","imagen":"NA","calificacion":3,"precio":"$","estado":"Abierto","descripcion":"Motel sencillo y cómodo.","horarios":"24h","telefono":"55 6789 0125","direccion":"Calle Hidalgo 1600, CDMX","web":"NA","menu":"NA","servicio":"Motel, Estacionamiento"},
  {"id":16,"nombre":"Hotel Barato CDMX","imagen":"NA","calificacion":2,"precio":"$","estado":"Abierto","descripcion":"Hotel económico para viajeros.","horarios":"24h","telefono":"55 7890 1236","direccion":"Av. Madero 1800, CDMX","web":"NA","menu":"NA","servicio":"Hotel, WiFi"},
  {"id":17,"nombre":"Hostal La Plaza CDMX","imagen":"NA","calificacion":3,"precio":"$","estado":"Abierto","descripcion":"Hostal frente a la plaza principal.","horarios":"24h","telefono":"55 8901 2347","direccion":"Av. Insurgentes 1900, CDMX","web":"NA","menu":"NA","servicio":"Hostal, WiFi"},
  {"id":18,"nombre":"Hotel de la Plaza CDMX","imagen":"NA","calificacion":4,"precio":"$$","estado":"Abierto","descripcion":"Hotel con vista a la plaza.","horarios":"24h","telefono":"55 9012 3458","direccion":"Plaza Principal 1, CDMX","web":"NA","menu":"NA","servicio":"Hotel, Vista"}
] 